README.md
setup.py
MomwhyareyouhereWebsite.egg-info/PKG-INFO
MomwhyareyouhereWebsite.egg-info/SOURCES.txt
MomwhyareyouhereWebsite.egg-info/dependency_links.txt
MomwhyareyouhereWebsite.egg-info/top_level.txt
mom_website/MomwhyareyouhereWebsite.py
mom_website/__init__.py